odoo/addons/ssi_l10n_id_taxform_bukti_potong_pph_f113301/README.rst
odoo/addons/ssi_l10n_id_taxform_bukti_potong_pph_f113301/__init__.py
odoo/addons/ssi_l10n_id_taxform_bukti_potong_pph_f113301/__manifest__.py
odoo/addons/ssi_l10n_id_taxform_bukti_potong_pph_f113301/data/account_journal_data.xml
odoo/addons/ssi_l10n_id_taxform_bukti_potong_pph_f113301/data/approval_template_data.xml
odoo/addons/ssi_l10n_id_taxform_bukti_potong_pph_f113301/data/ir_sequence_data.xml
odoo/addons/ssi_l10n_id_taxform_bukti_potong_pph_f113301/data/l10n_id_bukti_potong_type.xml
odoo/addons/ssi_l10n_id_taxform_bukti_potong_pph_f113301/data/policy_template_data.xml
odoo/addons/ssi_l10n_id_taxform_bukti_potong_pph_f113301/data/sequence_template_data.xml
odoo/addons/ssi_l10n_id_taxform_bukti_potong_pph_f113301/demo/account_account_demo.xml
odoo/addons/ssi_l10n_id_taxform_bukti_potong_pph_f113301/demo/account_journal_demo.xml
odoo/addons/ssi_l10n_id_taxform_bukti_potong_pph_f113301/demo/account_tax_demo.xml
odoo/addons/ssi_l10n_id_taxform_bukti_potong_pph_f113301/demo/l10n_id_bukti_potong_type_demo.xml
odoo/addons/ssi_l10n_id_taxform_bukti_potong_pph_f113301/models/__init__.py
odoo/addons/ssi_l10n_id_taxform_bukti_potong_pph_f113301/models/bukti_potong_pph_f113301_out.py
odoo/addons/ssi_l10n_id_taxform_bukti_potong_pph_f113301/models/bukti_potong_pph_f113301_out_line.py
odoo/addons/ssi_l10n_id_taxform_bukti_potong_pph_f113301/security/ir.model.access.csv
odoo/addons/ssi_l10n_id_taxform_bukti_potong_pph_f113301/security/ir_module_category_data.xml
odoo/addons/ssi_l10n_id_taxform_bukti_potong_pph_f113301/security/ir_rule_data.xml
odoo/addons/ssi_l10n_id_taxform_bukti_potong_pph_f113301/security/res_group_data.xml
odoo/addons/ssi_l10n_id_taxform_bukti_potong_pph_f113301/static/description/icon.png
odoo/addons/ssi_l10n_id_taxform_bukti_potong_pph_f113301/views/bukti_potong_pph_f113301_out_views.xml
odoo/addons/ssi_l10n_id_taxform_bukti_potong_pph_f113301/views/bukti_potong_pph_type_views.xml
odoo14_addon_ssi_l10n_id_taxform_bukti_potong_pph_f113301-14.0.1.5.0.dist-info/METADATA
odoo14_addon_ssi_l10n_id_taxform_bukti_potong_pph_f113301-14.0.1.5.0.dist-info/WHEEL
odoo14_addon_ssi_l10n_id_taxform_bukti_potong_pph_f113301-14.0.1.5.0.dist-info/top_level.txt
odoo14_addon_ssi_l10n_id_taxform_bukti_potong_pph_f113301-14.0.1.5.0.dist-info/RECORD
